passwordmanager/__init__.py
passwordmanager/cli.py
passwordmanager/password_ops.py
passwordmanager/security.py
passwordmanager/utils.py
passwordmanager/storage/__init__.py
passwordmanager_santhosh-0.2.0.dist-info/METADATA
passwordmanager_santhosh-0.2.0.dist-info/WHEEL
passwordmanager_santhosh-0.2.0.dist-info/entry_points.txt
passwordmanager_santhosh-0.2.0.dist-info/top_level.txt
passwordmanager_santhosh-0.2.0.dist-info/RECORD
